odoo/addons/product_catalog/README.rst
odoo/addons/product_catalog/__init__.py
odoo/addons/product_catalog/__manifest__.py
odoo/addons/product_catalog/controllers/__init__.py
odoo/addons/product_catalog/controllers/catalog.py
odoo/addons/product_catalog/i18n/it.po
odoo/addons/product_catalog/i18n/product_catalog.pot
odoo/addons/product_catalog/models/__init__.py
odoo/addons/product_catalog/models/product_catalog_mixin.py
odoo/addons/product_catalog/readme/CONTEXT.md
odoo/addons/product_catalog/readme/CONTRIBUTORS.md
odoo/addons/product_catalog/readme/DESCRIPTION.md
odoo/addons/product_catalog/readme/ROADMAP.md
odoo/addons/product_catalog/readme/USAGE.md
odoo/addons/product_catalog/static/description/icon.png
odoo/addons/product_catalog/static/description/index.html
odoo/addons/product_catalog/static/src/product_catalog/kanban_controller.esm.js
odoo/addons/product_catalog/static/src/product_catalog/kanban_model.esm.js
odoo/addons/product_catalog/static/src/product_catalog/kanban_record.esm.js
odoo/addons/product_catalog/static/src/product_catalog/kanban_record.xml
odoo/addons/product_catalog/static/src/product_catalog/kanban_renderer.esm.js
odoo/addons/product_catalog/static/src/product_catalog/kanban_renderer.xml
odoo/addons/product_catalog/static/src/product_catalog/kanban_view.esm.js
odoo/addons/product_catalog/static/src/product_catalog/kanban_view_buttons.xml
odoo/addons/product_catalog/static/src/product_catalog/order_line/order_line.esm.js
odoo/addons/product_catalog/static/src/product_catalog/order_line/order_line.scss
odoo/addons/product_catalog/static/src/product_catalog/order_line/order_line.xml
odoo/addons/product_catalog/static/src/product_catalog/search/search_panel.esm.js
odoo/addons/product_catalog/static/src/product_catalog/search/search_panel.xml
odoo/addons/product_catalog/views/product_views.xml
odoo_addon_product_catalog-16.0.1.0.0.5.dist-info/METADATA
odoo_addon_product_catalog-16.0.1.0.0.5.dist-info/WHEEL
odoo_addon_product_catalog-16.0.1.0.0.5.dist-info/top_level.txt
odoo_addon_product_catalog-16.0.1.0.0.5.dist-info/RECORD
